shaperglot-1.2.0.dist-info/METADATA
shaperglot-1.2.0.dist-info/WHEEL
shaperglot-1.2.0.dist-info/entry_points.txt
shaperglot/__init__.py
shaperglot/__main__.py
shaperglot/_shaperglot.cpython-312-aarch64-linux-gnu.so
shaperglot/cli/__init__.py
shaperglot/cli/check.py
shaperglot/cli/describe.py
shaperglot/cli/report.py
shaperglot/cli/whatuses.py
shaperglot-1.2.0.dist-info/RECORD
